{
    "category": "company",
    "datetime": 1745446585,
    "headline": "AMD Jumped Today -- Is the Artificial Intelligence (AI) Stock a Buy?",
    "id": 134059504,
    "image": "https://s.yimg.com/rz/stage/p/yahoo_finance_en-US_h_p_finance_2.png",
    "related": "AMD",
    "source": "Yahoo",
    "summary": "Advanced Micro Devices (NASDAQ: AMD) stock closed out Wednesday's daily session with big gains.  The semiconductor company's share price rose 4.9% in a day of trading that saw the S&P 500 index climb 1.6% and the Nasdaq Composite rise 2.5%.  AMD stock jumped today following developments that suggest that the trade war between the U.S. and China could see a meaningful de-escalation in the not-too-distant future.",
    "url": "https://finnhub.io/api/news?id=85cd48aa6a343b372a28c903df46ab5f174406b52cdd0f7283a6ddc155659b98"
}