{
    "category": "company",
    "datetime": 1744891717,
    "headline": "Is Advanced Micro Devices (AMD) A Reddit Stock with High Potential?",
    "id": 133958591,
    "image": "https://s.yimg.com/rz/stage/p/yahoo_finance_en-US_h_p_finance_2.png",
    "related": "AMD",
    "source": "Yahoo",
    "summary": "We recently published a list of the 12 Reddit Stocks with High Potential. In this article, we are going to take a look at where Advanced Micro Devices, Inc. (NASDAQ:AMD) stands against other Reddit stocks with high potential. On April 15, Monica Guerra, Morgan Stanley Wealth Management Head of US Policy, joined ‘Closing Bell Overtime’ […]",
    "url": "https://finnhub.io/api/news?id=8bcf7d9e3d53cd36b3893cdd814f63e1b9fa0609af0bdf53a6d22acccd0797eb"
}