{
    "category": "company",
    "datetime": 1744699570,
    "headline": "AMD to produce its processors with TSMC in Arizona",
    "id": 133919991,
    "image": "",
    "related": "AMD",
    "source": "Finnhub",
    "summary": "With the threat of tariffs hanging over the semiconductor sector, AMD is moving its production completely to TSMC's US plant in Arizona. This initiative was taken ahead of Trump's decisions, but can...",
    "url": "https://finnhub.io/api/news?id=e3891c73e7cb6c5ac157503765147b9765270a2d08b9e7cb20560c7b16ed740d"
}