{
    "category": "company",
    "datetime": 1742549671,
    "headline": "Micron: A Dirt-Cheap AI Growth Play",
    "id": 133299032,
    "image": "https://static.seekingalpha.com/cdn/s3/uploads/getty_images/1998660059/image_1998660059.jpg?io=getty-c-w1536",
    "related": "MU",
    "source": "SeekingAlpha",
    "summary": "Micron's strong earnings and future outlook make it a top pick for AI exposure. Learn why MU stock is attractive at a low P/E ratio compared to NVDA and AMD.",
    "url": "https://finnhub.io/api/news?id=a8ea4494e16db66ae81fd2348edcf5ad2bfc7939421bf8e20b1e519868afbc4c"
}