{
    "category": "company",
    "datetime": 1745453163,
    "headline": "Micron Technology, Inc. (MU): A Bull Case Theory",
    "id": 134059668,
    "image": "https://s.yimg.com/rz/stage/p/yahoo_finance_en-US_h_p_finance_2.png",
    "related": "MU",
    "source": "Yahoo",
    "summary": "We came across a bullish thesis on Micron Technology, Inc. (MU) on Substack by Oliver | MMMT Wealth. In this article, we will summarize the bulls’ thesis on MU. Micron Technology, Inc. (MU)’s share was trading at $70.21 as of April 22nd. MU’s trailing and forward P/E were 16.80 and 10.28 respectively according to Yahoo Finance. Micron […]",
    "url": "https://finnhub.io/api/news?id=a67886649c80c75e97197b384f4ae45ae86c04d5651862871b1b8f0776ec647b"
}