{
    "category": "company",
    "datetime": 1715102040,
    "headline": "Tesla Stock Drops as Government Ramps Up Self-Driving Oversight",
    "id": 127507378,
    "image": "https://s.yimg.com/ny/api/res/1.2/50w.c6NiTf05zldj8k.ToA--/YXBwaWQ9aGlnaGxhbmRlcjt3PTEyMDA7aD02MDA-/https://media.zenfs.com/en/Barrons.com/43610abfedd5f862d79f6acd79dc2775",
    "related": "TSLA",
    "source": "Yahoo",
    "summary": "Tesla stock was falling  Tuesday as Chinese sales numbers—and results from electric-vehicle start-up  Lucid  —weighed on investor sentiment.  In December, Tesla recalled some 2 million vehicles to update warnings to its driver-assistance systems and prevent misuse by drivers.  The National Highway Traffic Safety Administration, or NHTSA, recently opened an investigation into that recall to ensure the fixes were working.",
    "url": "https://finnhub.io/api/news?id=b0e4b55c55df5ec4e2494e20bd051008184d0ff98b4d8ab2da7d302d45f63384"
}